{
  "case_id": "QXW8F67",
  "assessments": [
    {
      "image_id": "FOTDEV_63",
      "aprovada": false,
      "motivo": "A imagem não mostra o capô, mas sim o motor do veículo.",
      "qualidade_imagem": "alta",
      "corresponde_a_peca": false
    },
    {
      "image_id": "FOTDEV_64",
      "aprovada": true,
      "motivo": "Imagem utilizável para análise, apesar de não mostrar a peça inteira.",
      "qualidade_imagem": "media",
      "corresponde_a_peca": true
    },
    {
      "image_id": "FOTDEV_65",
      "aprovada": false,
      "motivo": "A imagem não mostra a peça 'tampa_porta_malas', mas sim um estepe.",
      "qualidade_imagem": "alta",
      "corresponde_a_peca": false
    },
    {
      "image_id": "FOTDEV_66",
      "aprovada": false,
      "motivo": "A imagem não mostra a roda dianteira direita, apenas o pneu.",
      "qualidade_imagem": "media",
      "corresponde_a_peca": false
    },
    {
      "image_id": "FOTDEV_67",
      "aprovada": true,
      "motivo": "Imagem utilizável para análise, apesar de não mostrar a peça inteira.",
      "qualidade_imagem": "media",
      "corresponde_a_peca": true
    },
    {
      "image_id": "FOTDEV_68",
      "aprovada": true,
      "motivo": "A imagem é utilizável para análise, apesar de não ser possível confirmar a correspondência exata da peça.",
      "qualidade_imagem": "media",
      "corresponde_a_peca": false
    },
    {
      "image_id": "FOTDEV_69",
      "aprovada": true,
      "motivo": "",
      "qualidade_imagem": "media",
      "corresponde_a_peca": true
    },
    {
      "image_id": "FOTDEV_70",
      "aprovada": true,
      "motivo": "",
      "qualidade_imagem": "media",
      "corresponde_a_peca": true
    },
    {
      "image_id": "FOTDEV_71",
      "aprovada": true,
      "motivo": "Imagem utilizável para análise, apesar de não estar perfeitamente centrada na peça.",
      "qualidade_imagem": "media",
      "corresponde_a_peca": true
    },
    {
      "image_id": "FOTDEV_72",
      "aprovada": false,
      "motivo": "A imagem não mostra a porta dianteira direita.",
      "qualidade_imagem": "alta",
      "corresponde_a_peca": false
    },
    {
      "image_id": "FOTDEV_73",
      "aprovada": true,
      "motivo": "",
      "qualidade_imagem": "alta",
      "corresponde_a_peca": true
    },
    {
      "image_id": "FOTDEV_74",
      "aprovada": false,
      "motivo": "A imagem está em um ângulo que não permite identificar claramente a roda dianteira direita.",
      "qualidade_imagem": "media",
      "corresponde_a_peca": false
    },
    {
      "image_id": "FOTDEV_75",
      "aprovada": true,
      "motivo": "Imagem utilizável para análise, mostra a peça dianteira do carro.",
      "qualidade_imagem": "media",
      "corresponde_a_peca": true
    },
    {
      "image_id": "FOTDEV_83",
      "aprovada": true,
      "motivo": "Imagem utilizável para análise, apesar de não mostrar claramente a porta traseira direita.",
      "qualidade_imagem": "media",
      "corresponde_a_peca": false
    },
    {
      "image_id": "FOTDEV_84",
      "aprovada": true,
      "motivo": "Imagem utilizável para análise, apesar de não mostrar claramente a porta traseira direita.",
      "qualidade_imagem": "media",
      "corresponde_a_peca": false
    },
    {
      "image_id": "FOTDEV_85",
      "aprovada": true,
      "motivo": "Imagem utilizável para análise, apesar de não ser possível confirmar a correspondência exata da peça.",
      "qualidade_imagem": "media",
      "corresponde_a_peca": false
    },
    {
      "image_id": "FOTDEV_86",
      "aprovada": true,
      "motivo": "",
      "qualidade_imagem": "media",
      "corresponde_a_peca": true
    },
    {
      "image_id": "FOTDEV_87",
      "aprovada": true,
      "motivo": "Imagem utilizável para análise, apesar de não mostrar a peça frontal completa.",
      "qualidade_imagem": "media",
      "corresponde_a_peca": true
    },
    {
      "image_id": "FOTDEV_88",
      "aprovada": true,
      "motivo": "",
      "qualidade_imagem": "media",
      "corresponde_a_peca": true
    },
    {
      "image_id": "FOTDEV_89",
      "aprovada": false,
      "motivo": "Imagem de qualidade baixa, com reflexos que dificultam a visualização da peça.",
      "qualidade_imagem": "baixa",
      "corresponde_a_peca": true
    },
    {
      "image_id": "FOTDEV_90",
      "aprovada": true,
      "motivo": "",
      "qualidade_imagem": "media",
      "corresponde_a_peca": true
    },
    {
      "image_id": "FOTDEV_91",
      "aprovada": true,
      "motivo": "Imagem utilizável para análise, apesar de não mostrar claramente a peça.",
      "qualidade_imagem": "media",
      "corresponde_a_peca": false
    },
    {
      "image_id": "FOTDEV_92",
      "aprovada": false,
      "motivo": "A imagem não mostra claramente o paralama traseiro direito.",
      "qualidade_imagem": "media",
      "corresponde_a_peca": false
    },
    {
      "image_id": "FOTDEV_93",
      "aprovada": false,
      "motivo": "A imagem não mostra uma peça automotiva, mas sim um documento de identidade.",
      "qualidade_imagem": "media",
      "corresponde_a_peca": false
    },
    {
      "image_id": "FOTDEV_94",
      "aprovada": true,
      "motivo": "",
      "qualidade_imagem": "media",
      "corresponde_a_peca": true
    },
    {
      "image_id": "FOTDEV_95",
      "aprovada": true,
      "motivo": "",
      "qualidade_imagem": "media",
      "corresponde_a_peca": true
    },
    {
      "image_id": "FOTDEV_96",
      "aprovada": false,
      "motivo": "A imagem não mostra a roda dianteira esquerda, apenas o pneu.",
      "qualidade_imagem": "media",
      "corresponde_a_peca": false
    },
    {
      "image_id": "FOTDEV_97",
      "aprovada": false,
      "motivo": "A imagem não mostra a roda dianteira direita, apenas o pneu.",
      "qualidade_imagem": "media",
      "corresponde_a_peca": false
    },
    {
      "image_id": "FOTDEV_98",
      "aprovada": true,
      "motivo": "",
      "qualidade_imagem": "alta",
      "corresponde_a_peca": true
    },
    {
      "image_id": "FOTDEV_99",
      "aprovada": true,
      "motivo": "",
      "qualidade_imagem": "media",
      "corresponde_a_peca": true
    }
  ]
}