{
  "case_id": "RUN5B13",
  "assessments": [
    {
      "image_id": "FOTDEV_1",
      "aprovada": false,
      "motivo": "A imagem não mostra claramente o interior do veículo.",
      "qualidade_imagem": "media",
      "corresponde_a_peca": false
    },
    {
      "image_id": "FOTDEV_10",
      "aprovada": true,
      "motivo": "A imagem não mostra a peça indicada (parabrisa).",
      "qualidade_imagem": "alta",
      "corresponde_a_peca": false
    },
    {
      "image_id": "FOTDEV_11",
      "aprovada": true,
      "motivo": "A imagem não mostra o parabrisa, apenas a parte frontal do veículo.",
      "qualidade_imagem": "media",
      "corresponde_a_peca": false
    },
    {
      "image_id": "FOTDEV_12",
      "aprovada": false,
      "motivo": "A imagem não mostra claramente a traseira do carro, focando em outra área.",
      "qualidade_imagem": "alta",
      "corresponde_a_peca": false
    },
    {
      "image_id": "FOTDEV_13",
      "aprovada": true,
      "motivo": "",
      "qualidade_imagem": "alta",
      "corresponde_a_peca": true
    },
    {
      "image_id": "FOTDEV_14",
      "aprovada": true,
      "motivo": "A imagem não mostra o parabrisa, mas sim um pneu e ferramentas.",
      "qualidade_imagem": "media",
      "corresponde_a_peca": false
    },
    {
      "image_id": "FOTDEV_15",
      "aprovada": true,
      "motivo": "",
      "qualidade_imagem": "alta",
      "corresponde_a_peca": true
    },
    {
      "image_id": "FOTDEV_16",
      "aprovada": true,
      "motivo": "",
      "qualidade_imagem": "alta",
      "corresponde_a_peca": true
    },
    {
      "image_id": "FOTDEV_17",
      "aprovada": false,
      "motivo": "A imagem não mostra claramente o vidro traseiro do veículo.",
      "qualidade_imagem": "media",
      "corresponde_a_peca": false
    },
    {
      "image_id": "FOTDEV_18",
      "aprovada": true,
      "motivo": "A imagem não mostra o parabrisa, mas sim o painel do veículo.",
      "qualidade_imagem": "media",
      "corresponde_a_peca": false
    },
    {
      "image_id": "FOTDEV_19",
      "aprovada": true,
      "motivo": "",
      "qualidade_imagem": "alta",
      "corresponde_a_peca": true
    },
    {
      "image_id": "FOTDEV_2",
      "aprovada": false,
      "motivo": "A imagem não mostra claramente o interior do veículo.",
      "qualidade_imagem": "media",
      "corresponde_a_peca": false
    },
    {
      "image_id": "FOTDEV_20",
      "aprovada": true,
      "motivo": "A imagem não mostra o parabrisa do veículo.",
      "qualidade_imagem": "media",
      "corresponde_a_peca": false
    },
    {
      "image_id": "FOTDEV_3",
      "aprovada": true,
      "motivo": "",
      "qualidade_imagem": "alta",
      "corresponde_a_peca": true
    },
    {
      "image_id": "FOTDEV_4",
      "aprovada": true,
      "motivo": "A imagem não mostra o parabrisa, apenas a lateral do carro.",
      "qualidade_imagem": "media",
      "corresponde_a_peca": false
    },
    {
      "image_id": "FOTDEV_5",
      "aprovada": false,
      "motivo": "A imagem não mostra o capô, mas sim o motor e componentes internos.",
      "qualidade_imagem": "media",
      "corresponde_a_peca": false
    },
    {
      "image_id": "FOTDEV_6",
      "aprovada": false,
      "motivo": "A imagem não mostra o retrovisor.",
      "qualidade_imagem": "media",
      "corresponde_a_peca": false
    },
    {
      "image_id": "FOTDEV_7",
      "aprovada": true,
      "motivo": "A imagem não mostra o parabrisa do veículo.",
      "qualidade_imagem": "media",
      "corresponde_a_peca": false
    },
    {
      "image_id": "FOTDEV_8",
      "aprovada": true,
      "motivo": "Imagem utilizável para análise de avaria no parabrisa.",
      "qualidade_imagem": "media",
      "corresponde_a_peca": true
    },
    {
      "image_id": "FOTDEV_9",
      "aprovada": false,
      "motivo": "A imagem não mostra claramente a roda traseira direita.",
      "qualidade_imagem": "media",
      "corresponde_a_peca": false
    }
  ]
}