{
  "case_id": "SHJ8A93",
  "assessments": [
    {
      "image_id": "FOTDEV_12",
      "aprovada": true,
      "motivo": "",
      "qualidade_imagem": "media",
      "corresponde_a_peca": true
    },
    {
      "image_id": "FOTDEV_13",
      "aprovada": false,
      "motivo": "Imagem não mostra claramente a roda dianteira direita.",
      "qualidade_imagem": "media",
      "corresponde_a_peca": false
    },
    {
      "image_id": "FOTDEV_14",
      "aprovada": true,
      "motivo": "A imagem é utilizável para análise, apesar de não mostrar a roda inteira.",
      "qualidade_imagem": "media",
      "corresponde_a_peca": false
    },
    {
      "image_id": "FOTDEV_15",
      "aprovada": true,
      "motivo": "",
      "qualidade_imagem": "alta",
      "corresponde_a_peca": true
    },
    {
      "image_id": "FOTDEV_16",
      "aprovada": true,
      "motivo": "",
      "qualidade_imagem": "media",
      "corresponde_a_peca": true
    },
    {
      "image_id": "FOTDEV_47",
      "aprovada": true,
      "motivo": "Imagem utilizável para análise, apesar de não ser possível confirmar a correspondência exata da peça.",
      "qualidade_imagem": "media",
      "corresponde_a_peca": false
    },
    {
      "image_id": "FOTDEV_48",
      "aprovada": true,
      "motivo": "",
      "qualidade_imagem": "media",
      "corresponde_a_peca": true
    },
    {
      "image_id": "FOTDEV_49",
      "aprovada": true,
      "motivo": "Imagem utilizável para análise, apesar de não mostrar claramente a peça traseira.",
      "qualidade_imagem": "media",
      "corresponde_a_peca": false
    },
    {
      "image_id": "FOTDEV_50",
      "aprovada": true,
      "motivo": "",
      "qualidade_imagem": "media",
      "corresponde_a_peca": true
    },
    {
      "image_id": "FOTDEV_51",
      "aprovada": false,
      "motivo": "Imagem de baixa qualidade e não mostra a peça traseira do carro.",
      "qualidade_imagem": "baixa",
      "corresponde_a_peca": false
    },
    {
      "image_id": "FOTDEV_52",
      "aprovada": false,
      "motivo": "Imagem de baixa qualidade e não mostra a roda dianteira direita.",
      "qualidade_imagem": "baixa",
      "corresponde_a_peca": false
    },
    {
      "image_id": "FOTDEV_53",
      "aprovada": false,
      "motivo": "A imagem não mostra claramente a porta dianteira direita.",
      "qualidade_imagem": "media",
      "corresponde_a_peca": false
    },
    {
      "image_id": "FOTDEV_54",
      "aprovada": false,
      "motivo": "Imagem não mostra claramente a porta traseira direita.",
      "qualidade_imagem": "media",
      "corresponde_a_peca": false
    },
    {
      "image_id": "FOTDEV_55",
      "aprovada": true,
      "motivo": "",
      "qualidade_imagem": "alta",
      "corresponde_a_peca": true
    },
    {
      "image_id": "FOTDEV_56",
      "aprovada": false,
      "motivo": "Imagem com reflexo excessivo e nitidez comprometida, dificultando a análise.",
      "qualidade_imagem": "baixa",
      "corresponde_a_peca": true
    },
    {
      "image_id": "FOTDEV_57",
      "aprovada": true,
      "motivo": "",
      "qualidade_imagem": "media",
      "corresponde_a_peca": true
    },
    {
      "image_id": "FOTDEV_58",
      "aprovada": true,
      "motivo": "A imagem é utilizável para análise, apesar de não mostrar a roda completa.",
      "qualidade_imagem": "media",
      "corresponde_a_peca": false
    },
    {
      "image_id": "FOTDEV_59",
      "aprovada": true,
      "motivo": "A imagem é utilizável para análise, apesar de não mostrar claramente a roda dianteira direita.",
      "qualidade_imagem": "media",
      "corresponde_a_peca": false
    },
    {
      "image_id": "FOTDEV_60",
      "aprovada": false,
      "motivo": "A imagem não mostra a peça interior, mas sim um documento de habilitação.",
      "qualidade_imagem": "media",
      "corresponde_a_peca": false
    }
  ]
}