{
  "case_id": "SJD3D91",
  "triagem": {
    "total_imagens": 22,
    "imagens_aprovadas_qualidade": 10
  },
  "peritos": {
    "perito_parachoque": {
      "imagens_usadas": [
        {
          "image_id": "FOTDEV_15",
          "part_id": "parachoque_traseiro",
          "view": "media"
        },
        {
          "image_id": "FOTDEV_24",
          "part_id": "parachoque_traseiro",
          "view": "media"
        }
      ],
      "resultado": {
        "nivel_dano": "sem_dano",
        "peca": "para-choques",
        "itens": [],
        "servicos": [],
        "preco_total": 0,
        "justificativa": "[DESCONSIDERADO POR CHECKLIST] traseiro: sem_dano (Imagem ignorada: qualidade/visibilidade insuficiente)",
        "fotos_analisadas": [
          "C:\\Users\\464800\\Localiza\\Caio Albanese - AGENTE_AVARIAS_DEVOLUCAO\\input\\SJD3D91\\Fotos\\FOTDEV_15.jpg",
          "C:\\Users\\464800\\Localiza\\Caio Albanese - AGENTE_AVARIAS_DEVOLUCAO\\input\\SJD3D91\\Fotos\\FOTDEV_24.jpg"
        ]
      }
    },
    "perito_emblemas": {
      "imagens_usadas": [
        {
          "image_id": "FOTDEV_15",
          "part_id": "parachoque_traseiro",
          "view": "media"
        },
        {
          "image_id": "FOTDEV_24",
          "part_id": "parachoque_traseiro",
          "view": "media"
        }
      ],
      "resultado": {
        "nivel_dano": "sem_dano",
        "peca": "emblemas (dianteiro/traseiro)",
        "servicos": [],
        "preco_total": 0,
        "justificativa": "[DESCONSIDERADO POR CHECKLIST] traseiro: O emblema da montadora FIAT está visível e intacto na parte traseira do veículo.",
        "fotos_analisadas": [
          "C:\\Users\\464800\\Localiza\\Caio Albanese - AGENTE_AVARIAS_DEVOLUCAO\\input\\SJD3D91\\Fotos\\FOTDEV_15.jpg"
        ]
      }
    },
    "perito_lataria": {
      "imagens_usadas": [
        {
          "image_id": "FOTDEV_18",
          "part_id": "retrovisor_esquerdo",
          "view": "media"
        },
        {
          "image_id": "FOTDEV_30",
          "part_id": "capo",
          "view": "media"
        },
        {
          "image_id": "FOTDEV_13",
          "part_id": "porta_traseira_direita",
          "view": "media"
        }
      ],
      "resultado": {
        "nivel_dano": "sem_dano",
        "peca": "lataria",
        "servicos": [],
        "preco_total": 0.0,
        "justificativa": "Sem evidência de dano em lataria nas fotos fornecidas.",
        "fotos_analisadas": [
          "C:\\Users\\464800\\Localiza\\Caio Albanese - AGENTE_AVARIAS_DEVOLUCAO\\input\\SJD3D91\\Fotos\\FOTDEV_18.jpg",
          "C:\\Users\\464800\\Localiza\\Caio Albanese - AGENTE_AVARIAS_DEVOLUCAO\\input\\SJD3D91\\Fotos\\FOTDEV_30.jpg",
          "C:\\Users\\464800\\Localiza\\Caio Albanese - AGENTE_AVARIAS_DEVOLUCAO\\input\\SJD3D91\\Fotos\\FOTDEV_13.jpg"
        ]
      }
    },
    "perito_vidros": {
      "resultado": {
        "erro": "nenhuma imagem elegivel"
      }
    },
    "perito_pneus_rodas": {
      "imagens_usadas": [
        {
          "image_id": "FOTDEV_22",
          "part_id": "roda_dianteira_direita",
          "view": "detalhe"
        }
      ],
      "resultado": {
        "nivel_dano": "sem_dano",
        "peca": "calota",
        "servicos": [],
        "preco_total": 0.0,
        "justificativa": "Sem danos identificados nas rodas.",
        "fotos_analisadas": [
          "C:\\Users\\464800\\Localiza\\Caio Albanese - AGENTE_AVARIAS_DEVOLUCAO\\input\\SJD3D91\\Fotos\\FOTDEV_22.jpg"
        ]
      }
    },
    "perito_interior": {
      "imagens_usadas": [
        {
          "image_id": "FOTDEV_27",
          "part_id": "interior",
          "view": "media"
        },
        {
          "image_id": "FOTDEV_17",
          "part_id": "interior",
          "view": "interior"
        }
      ],
      "resultado": {
        "nivel_dano": "sem_dano",
        "peca": "painel",
        "servicos": [],
        "preco_total": 0,
        "justificativa": "[DESCONSIDERADO POR CHECKLIST] Sem danos identificados.",
        "fotos_analisadas": [
          "C:\\Users\\464800\\Localiza\\Caio Albanese - AGENTE_AVARIAS_DEVOLUCAO\\input\\SJD3D91\\Fotos\\FOTDEV_27.jpg",
          "C:\\Users\\464800\\Localiza\\Caio Albanese - AGENTE_AVARIAS_DEVOLUCAO\\input\\SJD3D91\\Fotos\\FOTDEV_17.jpg"
        ]
      }
    },
    "perito_acessorios": {
      "imagens_usadas": [
        {
          "image_id": "FOTDEV_14",
          "part_id": "acessorios",
          "view": "media"
        }
      ],
      "resultado": {
        "nivel_dano": "sem_dano",
        "peca": "chave",
        "servicos": [],
        "preco_total": 0,
        "justificativa": "[DESCONSIDERADO POR CHECKLIST] A chave apresenta sinais de desgaste visíveis, como danos na parte externa, que podem comprometer seu funcionamento.",
        "fotos_analisadas": [
          "C:\\Users\\464800\\Localiza\\Caio Albanese - AGENTE_AVARIAS_DEVOLUCAO\\input\\SJD3D91\\Fotos\\FOTDEV_14.jpg"
        ]
      }
    }
  },
  "divergencias_checklist": [
    {
      "tipo": "checklist_vs_visao",
      "perito": "perito_lataria",
      "part_id": "porta_traseira_direita",
      "mensagem": "Checklist marcou avaria para esta peça, mas o perito retornou nivel_dano='sem_dano'. Recomendado revisar manualmente.",
      "image_ids": [
        "FOTDEV_13"
      ],
      "photo_paths": [
        "C:\\Users\\464800\\Localiza\\Caio Albanese - AGENTE_AVARIAS_DEVOLUCAO\\input\\SJD3D91\\Fotos\\FOTDEV_13.jpg"
      ]
    },
    {
      "tipo": "checklist_vs_visao",
      "perito": "perito_pneus_rodas",
      "part_id": "roda_dianteira_direita",
      "mensagem": "Checklist marcou avaria para esta peça, mas o perito retornou nivel_dano='sem_dano'. Recomendado revisar manualmente.",
      "image_ids": [
        "FOTDEV_22"
      ],
      "photo_paths": [
        "C:\\Users\\464800\\Localiza\\Caio Albanese - AGENTE_AVARIAS_DEVOLUCAO\\input\\SJD3D91\\Fotos\\FOTDEV_22.jpg"
      ]
    }
  ],
  "cobrancas_checklist_fallback": [
    {
      "descricao": "CHECKLIST — Avaria reportada na peça 'porta_traseira_direita' (REVISAR)",
      "valor": 0,
      "needs_human_review": true,
      "origin": "checklist_fallback",
      "part_id": "porta_traseira_direita",
      "fotos": [
        "C:\\Users\\464800\\Localiza\\Caio Albanese - AGENTE_AVARIAS_DEVOLUCAO\\input\\SJD3D91\\Fotos\\FOTDEV_13.jpg"
      ]
    },
    {
      "descricao": "CHECKLIST — Avaria reportada na peça 'roda_dianteira_direita' (REVISAR)",
      "valor": 0,
      "needs_human_review": true,
      "origin": "checklist_fallback",
      "part_id": "roda_dianteira_direita",
      "fotos": [
        "C:\\Users\\464800\\Localiza\\Caio Albanese - AGENTE_AVARIAS_DEVOLUCAO\\input\\SJD3D91\\Fotos\\FOTDEV_22.jpg"
      ]
    }
  ],
  "preco_total_geral": 0.0
}